{
  "project_info": {
    "project_number": "896555974474",
    "project_id": "nitrogapp-tubes",
    "storage_bucket": "nitrogapp-tubes.appspot.com"
  },
  "client": [
    {
      "client_info": {
        "mobilesdk_app_id": "1:896555974474:android:d13752bc5fcb0a1f140bb3",
        "android_client_info": {
          "package_name": "com.example.tugas_layout"
        }
      },
      "oauth_client": [
        {
          "client_id": "896555974474-0lctqnqt1mqhaiipsunl044jp46fddhd.apps.googleusercontent.com",
          "client_type": 1,
          "android_info": {
            "package_name": "com.example.tugas_layout",
            "certificate_hash": "319ff600cbc3409940dacc2d0151091f29d4a681"
          }
        },
        {
          "client_id": "896555974474-msdqma1ljjbsotf4fq7bmtj6c7h3liab.apps.googleusercontent.com",
          "client_type": 3
        }
      ],
      "api_key": [
        {
          "current_key": "AIzaSyDNMdzrclre9BnZ1cozrlppFV1dzbWhMjA"
        }
      ],
      "services": {
        "appinvite_service": {
          "other_platform_oauth_client": [
            {
              "client_id": "896555974474-msdqma1ljjbsotf4fq7bmtj6c7h3liab.apps.googleusercontent.com",
              "client_type": 3
            },
            {
              "client_id": "896555974474-a2nocb2c2pmrdrhf6jj8869n62dj1a9l.apps.googleusercontent.com",
              "client_type": 2,
              "ios_info": {
                "bundle_id": "com.example.tugasLayout.RunnerTests"
              }
            }
          ]
        }
      }
    }
  ],
  "configuration_version": "1"
}